isnalyser/__init__.py
isnalyser/abbrevation.py
isnalyser/colors.py
isnalyser/debug.py
isnalyser/graph.py
isnalyser/paths.py
isnalyser/ranking.py
isnalyser/example_data/transmissions_example.csv
isnalyser/example_data/transmitters_example.csv
isnalyser-0.1.0.dist-info/LICENSE
isnalyser-0.1.0.dist-info/METADATA
isnalyser-0.1.0.dist-info/WHEEL
isnalyser-0.1.0.dist-info/top_level.txt
isnalyser-0.1.0.dist-info/RECORD
