Metadata-Version: 2.1
Name: isnalyser
Version: 0.1.0
Summary: Create isnad graphs automatically.
Home-page: https://github.com/dhakara/isnalyser
Author: Maroussia Bednarkiewicz, Stefan Wezel, Álvaro Tejero Cantero
Author-email: maroussia.b@gmail.com
License: UNKNOWN
Platform: UNKNOWN
Requires-Python: >=3.5
Requires-Dist: pandas (>=0.24.2)
Requires-Dist: graphviz (>=0.11.1)
Requires-Dist: matplotlib (>=2.0.0)
Requires-Dist: numpy (>=1.12.0)
